selikup.py
selikup-1.0.1.dist-info/METADATA
selikup-1.0.1.dist-info/WHEEL
selikup-1.0.1.dist-info/top_level.txt
selikup-1.0.1.dist-info/RECORD
